calc_note/__init__.py
calc_note/display.py
calc_note-0.3.2.dist-info/LICENSE
calc_note-0.3.2.dist-info/METADATA
calc_note-0.3.2.dist-info/WHEEL
calc_note-0.3.2.dist-info/RECORD
