Metadata-Version: 2.1
Name: calc-note
Version: 0.3.2
Summary: Collection of utilities to ease the production of professional calculation notes using Python and Jupyter.
Home-page: https://pypi.org/project/calc-note/
License: MIT
Author: Michel Lavoie
Author-email: lavoie.michel@gmail.com
Requires-Python: >=3.9,<4.0
Classifier: License :: OSI Approved :: MIT License
Classifier: Programming Language :: Python :: 3
Classifier: Programming Language :: Python :: 3.9
Classifier: Programming Language :: Python :: 3.10
Classifier: Programming Language :: Python :: 3.11
Classifier: Programming Language :: Python :: 3.12
Requires-Dist: handcalcs (>=1.9.0,<2.0.0)
Requires-Dist: pandas (>=2.2.3,<3.0.0)
Requires-Dist: tabulate (>=0.9.0,<0.10.0)
Project-URL: Repository, https://github.com/miek770/calc_note
